<?xml version="1.0" encoding="utf-8" ?>
<dwsync>
<file name="menuBg.gif" server="bizsmarty.com/public_html/dash/" local="129925382551587838" remote="129925398000000000" />
<file name="ajax-loader.png" server="bizsmarty.com/public_html/dash/" local="129925382543347366" remote="129925398000000000" />
<file name="icons-18-black.png" server="bizsmarty.com/public_html/dash/" local="129925382545127468" remote="129925398000000000" />
<file name="icons-18-white.png" server="bizsmarty.com/public_html/dash/" local="129925382546587552" remote="129925398000000000" />
<file name="icons-36-black.png" server="bizsmarty.com/public_html/dash/" local="129925382548607667" remote="129925398000000000" />
<file name="icons-36-white.png" server="bizsmarty.com/public_html/dash/" local="129925382550187758" remote="129925398000000000" />
<file name="menuBtn.png" server="bizsmarty.com/public_html/dash/" local="129925382553047921" remote="129925398000000000" />
<file name="menuIconsSprite.png" server="bizsmarty.com/public_html/dash/" local="129925382554478003" remote="129925398000000000" />
</dwsync>